{
    "os": "Linux-3.10.0-693.5.2.el7.x86_64-x86_64-with-glibc2.17",
    "python": "3.9.13",
    "heartbeatAt": "2023-01-30T21:45:43.017483",
    "startedAt": "2023-01-30T21:45:41.697698",
    "docker": null,
    "gpu": "GeForce RTX 3090",
    "gpu_count": 1,
    "cpu_count": 20,
    "cuda": null,
    "args": [],
    "state": "running",
    "program": "/ssd-scratch/harsh21122/ContextPromptPart/train.py",
    "codePath": "train.py",
    "git": {
        "remote": "git@github.com:harsh21122/ContextPromptPart.git",
        "commit": "38f3d1f74910a1d9398b6b87a14cfae99541730f"
    },
    "email": "harsh21122@iiitd.ac.in",
    "root": "/ssd-scratch/harsh21122/ContextPromptPart",
    "host": "compute-0-3.local",
    "username": "harsh21122",
    "executable": "/home/harsh21122/.conda/envs/part/bin/python"
}
